LICENSE
MANIFEST.in
README.rst
setup.py
pynmmso/__init__.py
pynmmso/mpi_fitness_caller.py
pynmmso/multiprocessor_fitness_caller.py
pynmmso/pynmmso.py
pynmmso/sequential_fitness_caller.py
pynmmso/swarm.py
pynmmso.egg-info/PKG-INFO
pynmmso.egg-info/SOURCES.txt
pynmmso.egg-info/dependency_links.txt
pynmmso.egg-info/not-zip-safe
pynmmso.egg-info/requires.txt
pynmmso.egg-info/top_level.txt
pynmmso/listeners/__init__.py
pynmmso/listeners/base_listener.py
pynmmso/listeners/multi_listener.py
pynmmso/listeners/parallel_predictor_listener.py
pynmmso/listeners/trace_listener.py
pynmmso/wrappers/__init__.py
pynmmso/wrappers/uniform_range_problem.py