Metadata-Version: 1.1
Name: pynmmso
Version: 1.0.0
Summary: Multi-Modal Search with the Niching Migratory Multi-Swarm Optimizer
Home-page: https://github.com/EPCCed/pynmmso/wiki
Author: Ally Hume
Author-email: a.hume@epcc.ed.ac.uk
License: MIT
Keywords: optimization,optimisation,optimizer,optimiser,multimodal,multi-modal,GA,genetic
Platform: UNKNOWN
Classifier: Development Status :: 3 - Alpha
Classifier: License :: OSI Approved :: MIT License
Classifier: Programming Language :: Python :: 3 :: Only
Classifier: Topic :: Scientific/Engineering
Classifier: Operating System :: OS Independent
